CHANGES.txt
LICENSE
MANIFEST.in
pyodbc-ucs2.patch
setup.py
progress_sa/__init__.py
progress_sa/base.py
progress_sa/pyodbc.py
progress_sa.egg-info/PKG-INFO
progress_sa.egg-info/SOURCES.txt
progress_sa.egg-info/dependency_links.txt
progress_sa.egg-info/entry_points.txt
progress_sa.egg-info/not-zip-safe
progress_sa.egg-info/requires.txt
progress_sa.egg-info/top_level.txt