Metadata-Version: 1.1
Name: progress-sa
Version: 0.4.1
Summary: Minimal SQLAlchemy dialect for OpenEdge 10/Progress.
Home-page: http://bitbucket.org/dholth/progress_sa
Author: Daniel Holth
Author-email: dholth@fastmail.fm
License: MIT
Keywords: sqlalchemy database dialect odbc
Platform: UNKNOWN
Classifier: Development Status :: 3 - Alpha
Classifier: Intended Audience :: Developers
Classifier: Operating System :: OS Independent
Classifier: Topic :: Database :: Database Engines/Servers
